{"id":"08lfhd114sujdrdforphl88","title":"ADHD","desc":"","updated":1657374132195,"created":1650115517898,"custom":{},"fname":"reference.adhd","type":"note","vault":{"fsPath":".","name":"digital-garden","selfContained":true},"contentHash":"edc5296bc0852d3d4397e3f3da59cdc1","links":[{"type":"ref","from":{"fname":"reference.adhd","id":"08lfhd114sujdrdforphl88","vaultName":"digital-garden"},"value":"reference.adhd.toxic-productivity-advice","position":{"start":{"line":3,"column":1,"offset":8},"end":{"line":3,"column":73,"offset":80},"indent":[]},"xvault":false,"to":{"fname":"reference.adhd.toxic-productivity-advice","anchorHeader":"my-summary,1:#^summary_end"}}],"anchors":{"adhd":{"type":"header","text":"ADHD","value":"adhd","line":7,"column":0,"depth":1}},"children":["p9ajj164aqsttucvtczxm2h","905shak1vb7e22tsxb227os"],"parent":"s2najqf438p0efaqmajbj9g","data":{}}
