{"id":"3kbydz8ke41roqaytuzvekh","title":"Chi Square Test","desc":"","updated":1667109986554,"created":1667109236155,"custom":{},"fname":"concepts.statistics.chi-square-test","type":"note","vault":{"fsPath":".","name":"digital-garden","selfContained":true},"contentHash":"81748b9c34e99b5053128a937fdc9753","links":[],"anchors":{"chi2-test":{"type":"header","text":"$$\\chi^2$$ Test","value":"chi2-test","line":7,"column":0,"depth":1},"goodness-of-fit-test":{"type":"header","text":"Goodness of Fit Test","value":"goodness-of-fit-test","line":21,"column":0,"depth":2},"table-of-significant-values":{"type":"header","text":"Table of Significant values","value":"table-of-significant-values","line":33,"column":0,"depth":2}},"children":[],"parent":"292e06p0y7xaa0eaii8uol9","data":{}}
