{"id":"de334ocdql3hn8j2kzrjxv7","title":"David Allen - Getting Things Done","desc":"","updated":1653217162438,"created":1653213979186,"custom":{},"fname":"reference.literature-notes.david-allen-getting-things-done","type":"note","vault":{"fsPath":".","name":"digital-garden","selfContained":true},"contentHash":"f5dc97d8795499d86b87a622f3e2fa3d","links":[{"from":{"fname":"now","id":"tu102fn6psvc3ef33p2jl5p","vaultName":"digital-garden"},"type":"backlink","position":{"start":{"line":13,"column":3,"offset":464},"end":{"line":13,"column":65,"offset":526},"indent":[]},"value":"reference.literature-notes.david-allen-getting-things-done"}],"anchors":{"david-allen---getting-things-done":{"type":"header","text":"David Allen - Getting Things Done","value":"david-allen---getting-things-done","line":8,"column":0,"depth":1},"basic-principles":{"type":"header","text":"Basic Principles","value":"basic-principles","line":16,"column":0,"depth":2},"our-live-and-work-is-complex-and-fast-paced":{"type":"header","text":"Our live and work is complex and fast-paced","value":"our-live-and-work-is-complex-and-fast-paced","line":22,"column":0,"depth":2},"focusing-on-the-bigger-picture-is-hard":{"type":"header","text":"Focusing on the bigger picture is hard","value":"focusing-on-the-bigger-picture-is-hard","line":35,"column":0,"depth":2},"quotes":{"type":"header","text":"Quotes","value":"quotes","line":42,"column":0,"depth":2}},"children":[],"parent":"3py39wn744dk1jzjl6onij3","data":{},"schema":{"schemaId":"j6hkamrk5ztc409qoxyb4jn","moduleId":"reference"}}
