{"id":"ghr5z4vpk0vf4qk69j7tcjt","title":"Handle XML","desc":"","updated":1652351301887,"created":1652351150017,"custom":{},"fname":"reference.dev.python.how-to.handle-xml","type":"note","vault":{"fsPath":".","name":"digital-garden","selfContained":true},"contentHash":"2e16bd4763a33f33a3c6472f7986978a","links":[],"anchors":{"handle-xml":{"type":"header","text":"Handle XML","value":"handle-xml","line":8,"column":0,"depth":1},"build-xml-trees":{"type":"header","text":"Build XML Trees","value":"build-xml-trees","line":10,"column":0,"depth":2}},"children":[],"parent":"1304hhhykir83hboxuh3maf","data":{}}
